sinfra/metadata.py
sinfra/cli/__init__.py
sinfra_tools-0.0.1.dist-info/METADATA
sinfra_tools-0.0.1.dist-info/WHEEL
sinfra_tools-0.0.1.dist-info/entry_points.txt
sinfra_tools-0.0.1.dist-info/RECORD
