Metadata-Version: 2.4
Name: sinfra-tools
Version: 0.0.1
Summary: A collection of tools for Sinfra
Project-URL: Source, https://gitlab.jsc.fz-juelich.de/sinfra/sinfra-tools
Author-email: Jayesh Badwaik <j.badwaik@fz-juelich.de>
License-Expression: Apache-2.0
Requires-Dist: livereload
Requires-Dist: pexpect
Requires-Dist: ruamel-yaml==0.18.15
Requires-Dist: semver
